{
    "name": "Todo",
    "fields": [
        {
            "fieldName": "title",
            "fieldType": "String"
        },
        {
            "fieldName": "description",
            "fieldType": "String"
        },
        {
            "fieldName": "complete",
            "fieldType": "Boolean"
        }
    ],
    "relationships": [],
    "changelogDate": "20191208190312",
    "entityTableName": "todo",
    "dto": "no",
    "pagination": "no",
    "service": "no",
    "jpaMetamodelFiltering": false,
    "fluentMethods": true,
    "readOnly": false,
    "clientRootFolder": "",
    "applications": "*"
}